shmlock-4.4.4.dist-info/METADATA
shmlock-4.4.4.dist-info/WHEEL
shmlock-4.4.4.dist-info/entry_points.txt
shmlock-4.4.4.dist-info/licenses/LICENSE.txt
shmlock/__init__.py
shmlock/shmlock_base_logger.py
shmlock/shmlock_config.py
shmlock/shmlock_exceptions.py
shmlock/shmlock_main.py
shmlock/shmlock_monkey_patch.py
shmlock/shmlock_uuid.py
shmlock/shmlock_warnings.py
shmlock-4.4.4.dist-info/RECORD
