Metadata-Version: 2.1
Name: shmlock
Version: 4.4.4
Summary: This module provides an inter-process lock implementation, eliminating the need to pass around objects for synchronization. Under the hood, the module leverages the shared_memory module.
Author-Email: Fabian Krumm <ghub_fk@gmx.de>
Classifier: Programming Language :: Python :: 3
Classifier: License :: OSI Approved :: BSD License
Classifier: Operating System :: OS Independent
Project-URL: homepage, https://github.com/fwkrumm/shmlock
Requires-Python: >=3.8
Requires-Dist: pywin32<400,>300; platform_system == "Windows"
Provides-Extra: membar
Requires-Dist: pymembar; extra == "membar"
